LICENSE.txt
MANIFEST.in
Makefile
README.md
setup.py
test.sh
test_file.ogg
test_tooltool.py
tooltool.py
docs/deployment/relengapi-tooltool/index.rst
docs/usage/relengapi-tooltool/index.rst
relengapi/__init__.py
relengapi/blueprints/__init__.py
relengapi/blueprints/tooltool/__init__.py
relengapi/blueprints/tooltool/grooming.py
relengapi/blueprints/tooltool/tables.py
relengapi/blueprints/tooltool/test_grooming.py
relengapi/blueprints/tooltool/test_tables.py
relengapi/blueprints/tooltool/test_tooltool.py
relengapi/blueprints/tooltool/test_util.py
relengapi/blueprints/tooltool/types.py
relengapi/blueprints/tooltool/util.py
relengapi/blueprints/tooltool/static/tooltool.css
relengapi/blueprints/tooltool/static/tooltool.html
relengapi/blueprints/tooltool/static/tooltool.js
relengapi/blueprints/tooltool/static/tt-result-batch.html
relengapi/blueprints/tooltool/static/tt-result-file.html
relengapi/blueprints/tooltool/templates/tooltool_root_widget.html
relengapi_tooltool.egg-info/PKG-INFO
relengapi_tooltool.egg-info/SOURCES.txt
relengapi_tooltool.egg-info/dependency_links.txt
relengapi_tooltool.egg-info/entry_points.txt
relengapi_tooltool.egg-info/namespace_packages.txt
relengapi_tooltool.egg-info/requires.txt
relengapi_tooltool.egg-info/top_level.txt