Metadata-Version: 1.0
Name: relengapi-tooltool
Version: 1.0.0
Summary: Secure, cache-friendly access to large binary blobs for builds and tests
Home-page: https://git.mozilla.org/?p=build/tooltool.git
Author: John Ford
Author-email: jhford@mozilla.com
License: MPL2
Platform: UNKNOWN
